odoo/addons/l10n_es_genci_stock_picking_report_valued/README.rst
odoo/addons/l10n_es_genci_stock_picking_report_valued/__init__.py
odoo/addons/l10n_es_genci_stock_picking_report_valued/__manifest__.py
odoo/addons/l10n_es_genci_stock_picking_report_valued/i18n/ca.po
odoo/addons/l10n_es_genci_stock_picking_report_valued/i18n/es.po
odoo/addons/l10n_es_genci_stock_picking_report_valued/models/__init__.py
odoo/addons/l10n_es_genci_stock_picking_report_valued/models/stock_move_line.py
odoo/addons/l10n_es_genci_stock_picking_report_valued/models/stock_picking.py
odoo/addons/l10n_es_genci_stock_picking_report_valued/readme/CONFIGURE.md
odoo/addons/l10n_es_genci_stock_picking_report_valued/readme/CONTRIBUTORS.md
odoo/addons/l10n_es_genci_stock_picking_report_valued/readme/DESCRIPTION.md
odoo/addons/l10n_es_genci_stock_picking_report_valued/readme/INSTALL.md
odoo/addons/l10n_es_genci_stock_picking_report_valued/readme/USAGE.md
odoo/addons/l10n_es_genci_stock_picking_report_valued/report/stock_picking_report_valued_template.xml
odoo/addons/l10n_es_genci_stock_picking_report_valued/static/description/icon.png
odoo/addons/l10n_es_genci_stock_picking_report_valued/static/description/index.html
odoo/addons/l10n_es_genci_stock_picking_report_valued/tests/__init__.py
odoo/addons/l10n_es_genci_stock_picking_report_valued/tests/test_l10n_es_genci_stock_picking_report_valued.py
odoo_addon_l10n_es_genci_stock_picking_report_valued-16.0.1.0.0.1.dist-info/METADATA
odoo_addon_l10n_es_genci_stock_picking_report_valued-16.0.1.0.0.1.dist-info/WHEEL
odoo_addon_l10n_es_genci_stock_picking_report_valued-16.0.1.0.0.1.dist-info/top_level.txt
odoo_addon_l10n_es_genci_stock_picking_report_valued-16.0.1.0.0.1.dist-info/RECORD
